cryptox/__init__.py
cryptox/market.py
cryptox/private/__init__.py
cryptox/public/__init__.py
cryptox/public/common/__init__.py
cryptox/public/common/common.py
cryptox/public/day_volume/__init__.py
cryptox/public/day_volume/day_volume.py
cryptox/public/get_currency_pairs/__init__.py
cryptox/public/get_currency_pairs/get_currency_pairs.py
cryptox/public/order_book/__init__.py
cryptox/public/order_book/order_book.py
cryptox/public/trade_history/__init__.py
cryptox/public/trade_history/trade_history.py
cryptox/sockets/__init__.py
cryptox-0.2.0.dist-info/DESCRIPTION.rst
cryptox-0.2.0.dist-info/METADATA
cryptox-0.2.0.dist-info/RECORD
cryptox-0.2.0.dist-info/WHEEL
cryptox-0.2.0.dist-info/metadata.json
cryptox-0.2.0.dist-info/top_level.txt
tests/__init__.py
tests/context.py
tests/test_basic.py
