Metadata-Version: 2.0
Name: cryptox
Version: 0.2.0
Summary: Python module for cryptocurrency analysis and trading
Home-page: https://bitbucket.org/blevine11/cryptox
Author: Benjamin Levine
Author-email: benjamin.r.levine@gmail.com
License: MIT
Keywords: cryptocurrency exchange module
Platform: UNKNOWN
Classifier: Development Status :: 1 - Planning
Classifier: Intended Audience :: Developers
Classifier: License :: OSI Approved :: MIT License
Classifier: Programming Language :: Python :: 2
Classifier: Programming Language :: Python :: 2.7
Classifier: Programming Language :: Python :: 3
Classifier: Programming Language :: Python :: 3.4
Classifier: Programming Language :: Python :: 3.5
Classifier: Programming Language :: Python :: 3.6
Requires-Dist: requests
